{
  "years": [
    2025,
    2026,
    2027,
    2028,
    2029,
    2030,
    2031,
    2032,
    2033,
    2034,
    2035,
    2036
  ],
  "baseline_payroll_b": [
    1534.3,
    1617.2,
    1693.7,
    1769.5,
    1846.4,
    1925.0,
    2005.3,
    2085.8,
    2167.6,
    2252.4,
    2340.2,
    2433.5
  ],
  "rate_response_2036": [
    {
      "k": 0.0,
      "payroll_b": 2434.4
    },
    {
      "k": 0.1,
      "payroll_b": 2662.2
    },
    {
      "k": 0.2,
      "payroll_b": 2890.0
    },
    {
      "k": 0.3,
      "payroll_b": 3117.9
    },
    {
      "k": 0.4,
      "payroll_b": 3345.7
    },
    {
      "k": 0.5,
      "payroll_b": 3573.5
    }
  ]
}